sxm/__init__.py
sxm/__main__.py
sxm/cli.py
sxm/client.py
sxm/http.py
sxm/models.py
sxm/py.typed
sxm-0.2.8.dist-info/entry_points.txt
sxm-0.2.8.dist-info/LICENSE
sxm-0.2.8.dist-info/WHEEL
sxm-0.2.8.dist-info/METADATA
sxm-0.2.8.dist-info/RECORD
